{"cameraMode":{"drawMode":0,"name":"Shaded","section":"Shading Mode"},"sceneLighting":true,"audioPlay":false,"sceneViewState":{"m_AlwaysRefresh":false,"showFog":true,"showSkybox":true,"showFlares":true,"showImageEffects":true,"showParticleSystems":true,"showVisualEffectGraphs":true,"m_FxEnabled":true},"in2DMode":false,"pivot":{"x":6.045563697814941,"y":0.37269338965415957,"z":1.5122194290161133},"rotation":{"x":0.11289751529693604,"y":-0.06701558828353882,"z":0.0076321689411997799,"w":0.9913151860237122},"size":2.222031831741333,"orthographic":false}